hungsql/__init__.py
hungsql-0.1.1.dist-info/licenses/LICENSE
hungsql-0.1.1.dist-info/METADATA
hungsql-0.1.1.dist-info/WHEEL
hungsql-0.1.1.dist-info/top_level.txt
hungsql-0.1.1.dist-info/RECORD
