Metadata-Version: 2.4
Name: hungsql
Version: 0.1.1
Summary: A SQL database engine that operates on CSV files
Author: T.Hung
License: MIT License
Requires-Python: >=3.10
License-File: LICENSE
Requires-Dist: fastapi
Requires-Dist: uvicorn[standard]
Requires-Dist: python-jose
Requires-Dist: bcrypt==3.2.2
Requires-Dist: python-multipart
Requires-Dist: lark
Requires-Dist: pandas
Requires-Dist: pydantic>=2.0
Requires-Dist: SQLAlchemy>=2.0
Requires-Dist: asyncpg
Requires-Dist: pydantic[email]
Requires-Dist: pytest
Requires-Dist: pytest-asyncio
Requires-Dist: PyYAML
Requires-Dist: requests
Dynamic: license-file
